thoplw/__init__.py
thoplw/counts.py
thoplw/description.py
thoplw/format.py
thoplw/linfo.py
thoplw/profile.py
thoplw-2024.1.25.dist-info/METADATA
thoplw-2024.1.25.dist-info/WHEEL
thoplw-2024.1.25.dist-info/licenses/LICENSE
thoplw-2024.1.25.dist-info/RECORD
