Metadata-Version: 2.1
Name: thoplw
Version: 2024.1.25
Summary: Count the layer-wise MACs and number of parameters of your PyTorch model.
Project-URL: Repository, https://github.com/tiskw/pytorch-op-counter-layerwise
Project-URL: Issues, https://github.com/tiskw/pytorch-op-counter-layerwise/issues
Author-email: Tetsuya Ishikawa <tiskw111@gmail.com>
License: MIT License
License-File: LICENSE
Classifier: Development Status :: 4 - Beta
Classifier: Intended Audience :: Developers
Classifier: License :: OSI Approved :: MIT License
Classifier: Operating System :: OS Independent
Classifier: Programming Language :: Python :: 3
Requires-Python: >=3.7
